{
  "items": [
    {
      "_id": "5720e0e6c4fa69cc0209241f",
      "created": 1461772518479,
      "updated": 1461772518479,
      "username": "username",
      "state": 0
    },
    {
      "_id": "57236795d8bcc545027cfbc5",
      "created": 1461938069256,
      "updated": 1461938069256,
      "username": "yoyoyoyo",
      "state": 0
    },
    {
      "_id": "572a10750dd4d07302bce71a",
      "created": 1462374517885,
      "updated": 1462374517885,
      "username": "pppppppp",
      "state": 1
    },
    {
      "_id": "572a12b490f1a6cb02b6ec48",
      "created": 1462375092041,
      "updated": 1462375092041,
      "username": "somebody",
      "state": 1
    },
    {
      "_id": "572f5424d75aa98f0f6cbbd7",
      "created": 1462719524991,
      "updated": 1462719524991,
      "username": "zzzzzzzz",
      "state": 1
    },
    {
      "_id": "572f542ed75aa98f0f6cbbd8",
      "created": 1462719534911,
      "updated": 1462719534911,
      "username": "xxxxxxxx",
      "state": 1
    },
    {
      "_id": "572f543bd75aa98f0f6cbbd9",
      "created": 1462719547808,
      "updated": 1462719547808,
      "username": "cccccccc",
      "state": 1
    },
    {
      "_id": "572f5445d75aa98f0f6cbbda",
      "created": 1462719557561,
      "updated": 1462719557561,
      "username": "vvvvvvvv",
      "state": 1
    },
    {
      "_id": "572f545ad75aa98f0f6cbbdc",
      "created": 1462719578918,
      "updated": 1462719578918,
      "username": "nnnnnnnn",
      "state": 1
    },
    {
      "_id": "572f8944d36df3c50483705b",
      "created": 1462733124254,
      "updated": 1462733124254,
      "username": "oooooooo",
      "state": 1
    }
  ],
  "count": 10
}
